setup.cfg
setup.py
isbn/__init__.py
isbn/hyphen.py
isbn/isbn.py
isbnid_fork.egg-info/PKG-INFO
isbnid_fork.egg-info/SOURCES.txt
isbnid_fork.egg-info/dependency_links.txt
isbnid_fork.egg-info/requires.txt
isbnid_fork.egg-info/top_level.txt