Metadata-Version: 1.1
Name: isbnid-fork
Version: 0.5.2
Summary: Python ISBN ids
Home-page: https://github.com/inspirehep/isbnid
Author: ISBNid GitHub
Author-email: admin@inspirehep.net
License: GPL
Keywords: ISBN
Platform: UNKNOWN
Classifier: Development Status :: 4 - Beta
Classifier: Intended Audience :: Developers
Classifier: Intended Audience :: Education
Classifier: License :: OSI Approved :: GNU Lesser General Public License v3 (LGPLv3)
Classifier: Programming Language :: Python :: 2.7
Classifier: Programming Language :: Python :: 3.5
Classifier: Topic :: Software Development :: Libraries :: Python Modules
Classifier: Topic :: Text Processing :: Indexing
